fast_starter/__init__.py
fast_starter/main.py
fast_starter-0.1.0.dist-info/METADATA
fast_starter-0.1.0.dist-info/WHEEL
fast_starter-0.1.0.dist-info/entry_points.txt
fast_starter-0.1.0.dist-info/top_level.txt
fast_starter-0.1.0.dist-info/RECORD
